shopify_auth/__init__.py
shopify_auth/apps.py
shopify_auth/backends.py
shopify_auth/context_processors.py
shopify_auth/decorators.py
shopify_auth/helpers.py
shopify_auth/models.py
shopify_auth/urls.py
shopify_auth/views.py
shopify_auth/templates/shopify_auth/iframe_redirect.html
shopify_auth/templates/shopify_auth/login.html
shopify_auth/tests/__init__.py
shopify_auth/tests/test_helpers.py
shopify_auth/tests/test_user.py
shopify_auth/tests/test_views.py
django_shopify_auth-0.9.0.dist-info/LICENSE
django_shopify_auth-0.9.0.dist-info/METADATA
django_shopify_auth-0.9.0.dist-info/WHEEL
django_shopify_auth-0.9.0.dist-info/top_level.txt
django_shopify_auth-0.9.0.dist-info/RECORD
