Metadata-Version: 2.1
Name: django-shopify-auth
Version: 0.9.0
Summary: A simple package for adding Shopify authentication to Django apps.
Home-page: https://github.com/discolabs/django-shopify-auth
Author: Gavin Ballard
Author-email: gavin@discolabs.com
License: MIT
Platform: UNKNOWN
Requires-Dist: django (>=1.8)
Requires-Dist: ShopifyAPI (>=2.1.5)
Requires-Dist: setuptools (>=5.7)
Requires-Dist: six (>=1.9.0)
